<?xml version="1.0" encoding="utf-8"?>
<hibernate-mapping assembly="GPS.DomainLayer" xmlns="urn:nhibernate-mapping-2.2">
  <class name="GPS.DomainLayer.Entities.SubMapRecord, GPS.DomainLayer" table="SubMapRecords" lazy="true" >
      <id name="Id" column="Id" >
          <generator class="native" />
      </id>
    <property name="AreaId" column="AreaId" />
    <property name="Classification" column="Classification" />
    <!--<property name="SubMapId" column="SubMapId" />-->
      <many-to-one name="SubMap" column="SubMapId" class="GPS.DomainLayer.Entities.SubMap, GPS.DomainLayer" />
    <property name="Value" column="Value" />
  </class>
</hibernate-mapping>